MANIFEST.in
README.txt
collective.workflowed-configure.zcml
setup.py
collective/__init__.py
collective.workflowed.egg-info/PKG-INFO
collective.workflowed.egg-info/SOURCES.txt
collective.workflowed.egg-info/dependency_links.txt
collective.workflowed.egg-info/entry_points.txt
collective.workflowed.egg-info/namespace_packages.txt
collective.workflowed.egg-info/not-zip-safe
collective.workflowed.egg-info/requires.txt
collective.workflowed.egg-info/top_level.txt
collective/workflowed/__init__.py
collective/workflowed/configure.zcml
collective/workflowed/profiles.zcml
collective/workflowed/setuphandlers.py
collective/workflowed/skins.zcml
collective/workflowed/version.txt
collective/workflowed/browser/__init__.py
collective/workflowed/browser/addworkflow.py
collective/workflowed/browser/configure.zcml
collective/workflowed/browser/state_permissions.pt
collective/workflowed/browser/toxml.py
collective/workflowed/browser/transition_props.pt
collective/workflowed/browser/workflowed.pt
collective/workflowed/browser/workflowed.py
collective/workflowed/browser/workflowed_iframe.pt
collective/workflowed/browser/images/README.txt
collective/workflowed/browser/images/page_white_code.png
collective/workflowed/browser/images/page_white_excel.png
collective/workflowed/browser/images/tick.png
collective/workflowed/browser/images/workflowed_icon.png
collective/workflowed/browser/stylesheets/README.txt
collective/workflowed/browser/stylesheets/grid_10.png
collective/workflowed/browser/stylesheets/main.css
collective/workflowed/profiles/default/actionicons.xml
collective/workflowed/profiles/default/collective.workflowed_various.txt
collective/workflowed/profiles/default/controlpanel.xml
collective/workflowed/profiles/default/cssregistry.xml
collective/workflowed/profiles/default/import_steps.xml
collective/workflowed/profiles/default/jsregistry.xml
collective/workflowed/profiles/default/metadata.xml
collective/workflowed/profiles/default/skins.xml
collective/workflowed/skins/collective_workflowed_custom_images/CONTENT.txt
collective/workflowed/skins/collective_workflowed_custom_images/ToolSelection.png
collective/workflowed/skins/collective_workflowed_custom_images/ToolState.png
collective/workflowed/skins/collective_workflowed_custom_images/ToolTransition.png
collective/workflowed/skins/collective_workflowed_custom_images/ToolWorklist.png
