Metadata-Version: 1.0
Name: collective.workflowed
Version: 1.1
Summary: A graphical workflow editor for Plone
Home-page: http://svn.plone.org/svn/collective/collective.workflowed
Author: Carlos de la Guardia
Author-email: cguardia@yahoo.com
License: GPL
Keywords: zope plone workflow editor
Platform: UNKNOWN
Classifier: Framework :: Plone
Classifier: Framework :: Zope2
Classifier: Framework :: Zope3
Classifier: Programming Language :: Python
Classifier: Topic :: Software Development :: Libraries :: Python Modules
